{"is_source_file": true, "description": "Simple txt file", "external_files": [], "external_methods": [], "published": [], "calls": [], "search-terms": [], "classes": [], "methods": [], "state": 2, "file_id": 10, "knowledge_revision": 25, "git_revision": "", "filename": "chat_backend/requirements.txt", "hash": "c576d2d8b2e67c6441f6b16f1f1b663c", "format-version": 4, "code-base-name": "https://github.com/kavia-common/conversai-chat-platform-12315-12325.git:kavia-main", "revision_history": [{"25": ""}]}